README.txt
setup.py
docs/HISTORY.txt
docs/LICENSE.GPL
docs/LICENSE.txt
src/example_profile.cfg
src/tinylogan.py
src/TinyLogAnalyzer.egg-info/PKG-INFO
src/TinyLogAnalyzer.egg-info/SOURCES.txt
src/TinyLogAnalyzer.egg-info/dependency_links.txt
src/TinyLogAnalyzer.egg-info/entry_points.txt
src/TinyLogAnalyzer.egg-info/not-zip-safe
src/TinyLogAnalyzer.egg-info/requires.txt
src/TinyLogAnalyzer.egg-info/top_level.txt