Metadata-Version: 1.0
Name: TinyLogAnalyzer
Version: 0.4.0
Summary: Command line utility for perform response time analysis onto HTTP access logs
Home-page: https://kpython-utils.svn.sourceforge.net/svnroot/kpython-utils/TinyLogAnalyzer/
Author: keul
Author-email: luca@keul.it
License: GPL
Keywords: file apache log response-time analyser http access
Platform: UNKNOWN
Classifier: Development Status :: 4 - Beta
Classifier: Intended Audience :: System Administrators
Classifier: License :: OSI Approved :: GNU General Public License (GPL)
Classifier: Operating System :: OS Independent
Classifier: Programming Language :: Python
Classifier: Topic :: Utilities
Classifier: Topic :: Internet :: Log Analysis
Classifier: Topic :: Internet :: WWW/HTTP
